pretix_telephone/__init__.py
pretix_telephone/exporter.py
pretix_telephone/shredder.py
pretix_telephone/signals.py
pretix_telephone/urls.py
pretix_telephone/views.py
pretix_telephone/locale/de/LC_MESSAGES/django.mo
pretix_telephone/locale/de/LC_MESSAGES/django.po
pretix_telephone/locale/de_Informal/.gitkeep
pretix_telephone/locale/de_Informal/LC_MESSAGES/django.mo
pretix_telephone/locale/de_Informal/LC_MESSAGES/django.po
pretix_telephone/static/pretix_telephone/.gitkeep
pretix_telephone/templates/pretix_telephone/.gitkeep
pretix_telephone/templates/pretix_telephone/orderdetails.html
pretix_telephone/templates/pretix_telephone/settings.html
pretix_telephone-2.4.0.dist-info/LICENSE
pretix_telephone-2.4.0.dist-info/METADATA
pretix_telephone-2.4.0.dist-info/WHEEL
pretix_telephone-2.4.0.dist-info/entry_points.txt
pretix_telephone-2.4.0.dist-info/top_level.txt
pretix_telephone-2.4.0.dist-info/RECORD
