Metadata-Version: 2.1
Name: pretix-telephone
Version: 2.4.0
Summary: This pretix plugin adds a contact question asking for the telephone number.
Home-page: https://github.com/felixrindt/pretix-telephone
Author: Felix Rindt
Author-email: felix@rindt.me
License: Apache Software License
Keywords: pretix plugin telephone
Platform: UNKNOWN
